<start>
  <something>
    <various>
      <ants>
        <death>-444415828</death>
        <establish am="who">-1364605923</establish>
        <dirty steel="themselves">gift</dirty>
        <thing some="what">
          <apes>668f38</apes>
        </thing>
        <thing some="what">
          <apes>668f38</apes>
        </thing>
        <thing some="what">
          <apes>668f38</apes>
        </thing>
        <thing some="what">
          <apes>668f38</apes>
        </thing>
        <thing some="what">
          <apes>668f38</apes>
        </thing>
        <thing some="what">
          <apes>668f38</apes>
        </thing>
        <shape drawn="salmon">
          <claws dawn="engine">
            <mix studying="new">1228972114</mix>
            <decide>
              <!--gift-->2136114887.636344
            </decide>
            <log suit="heat">189825216</log>
            <leader>317442565.91240597
                          <!--thrown zero origin every drove trip-->
            </leader>
            <brush>1217304743.8486605</brush>
            <iron>cover
                          <!--seven women plate-->
            </iron>
          </claws>
          <raw part="met">
            <everything scene="nose">1037506439</everything>
            <spider beat="function">1715777377</spider>
            <daily>just</daily>
            <!--mixture cap round-->
            <world>
              <!--beneath-->
              <saddle>world</saddle>
              <plastic>
                <truck skin="afternoon">-554236545.8829889</truck>
                <arrow>riding</arrow>
                <world>1019387530</world>
                <universe led="small">
                  <!--everything train-->forget
                </universe>
                <wise>opinion</wise>
                <progress>religious</progress>
              </plastic>
              <wherever>-482150725</wherever>
              <driven>due</driven>
              <rope lake="needle">heart</rope>
              <coat however="another">-696575458.4007263</coat>
            </world>
            <alike>-1548369962.2233067</alike>
            <making porch="gave">ants</making>
          </raw>
          <properly>1376700242</properly>
          <young>617140671</young>
          <name>kind
                      <!--wing yellow soil scientific amount taken-->
          </name>
          <crowd>known</crowd>
        </shape>
        <trip bottle="building">
          <!--same-->danger
        </trip>
        <!--success brown instead-->
        <loss egg="smallest">leaving</loss>
        <!--worried nobody-->
      </ants>
      <so mile="main">serve</so>
      <farther>partly</farther>
      <rather standard="daughter">
        <!--bone-->-572173481.9584856
      </rather>
      <purpose more="warm">
        <!--writer-->-212159828
      </purpose>
      <rubber>876373209</rubber>
    </various>
    <neck earn="college">dot</neck>
    <else speak="plural">hurt</else>
    <they>full</they>
    <!--highest-->
    <black>-482207114.1145582</black>
    <none>-1747293785.048098</none>
  </something>
  <something>
    <various>
      <ants>
        <death>-444415828</death>
        <establish am="who">-1364605923</establish>
        <dirty steel="themselves">gift</dirty>
        <shape drawn="salmon">
          <claws dawn="engine">
            <mix studying="new">1228972114</mix>
            <decide>
              <!--gift-->2136114887.636344
            </decide>
            <log suit="heat">189825216</log>
            <leader>317442565.91240597
                          <!--thrown zero origin every drove trip-->
            </leader>
            <brush>1217304743.8486605</brush>
            <iron>cover
                          <!--seven women plate-->
            </iron>
          </claws>
          <raw part="met">
            <everything scene="nose">1037506439</everything>
            <spider beat="function">1715777377</spider>
            <daily>just</daily>
            <!--mixture cap round-->
            <world>
              <!--beneath-->
              <saddle>world</saddle>
              <plastic>
                <truck skin="afternoon">-554236545.8829889</truck>
                <arrow>riding</arrow>
                <world>1019387530</world>
                <universe led="small">
                  <!--everything train-->forget
                </universe>
                <wise>opinion</wise>
                <progress>religious</progress>
              </plastic>
              <wherever>-482150725</wherever>
              <driven>due</driven>
              <rope lake="needle">heart</rope>
              <coat however="another">-696575458.4007263</coat>
            </world>
            <alike>-1548369962.2233067</alike>
            <making porch="gave">ants</making>
          </raw>
          <properly>1376700242</properly>
          <young>617140671</young>
          <name>kind
                      <!--wing yellow soil scientific amount taken-->
          </name>
          <crowd>known</crowd>
        </shape>
        <trip bottle="building">
          <!--same-->danger
        </trip>
        <!--success brown instead-->
        <loss egg="smallest">leaving</loss>
        <!--worried nobody-->
      </ants>
      <so mile="main">serve</so>
      <farther>partly</farther>
      <rather standard="daughter">
        <!--bone-->-572173481.9584856
      </rather>
      <purpose more="warm">
        <!--writer-->-212159828
      </purpose>
      <rubber>876373209</rubber>
    </various>
    <neck earn="college">dot</neck>
    <else speak="plural">hurt</else>
    <they>full</they>
    <!--highest-->
    <black>-482207114.1145582</black>
    <none>-1747293785.048098</none>
  </something>
  <something>
    <various>
      <ants>
        <death>-444415828</death>
        <establish am="who">-1364605923</establish>
        <dirty steel="themselves">gift</dirty>
        <shape drawn="salmon">
          <claws dawn="engine">
            <mix studying="new">1228972114</mix>
            <decide>
              <!--gift-->2136114887.636344
            </decide>
            <log suit="heat">189825216</log>
            <leader>317442565.91240597
                          <!--thrown zero origin every drove trip-->
            </leader>
            <brush>1217304743.8486605</brush>
            <iron>cover
                          <!--seven women plate-->
            </iron>
          </claws>
          <raw part="met">
            <everything scene="nose">1037506439</everything>
            <spider beat="function">1715777377</spider>
            <daily>just</daily>
            <!--mixture cap round-->
            <world>
              <!--beneath-->
              <saddle>world</saddle>
              <plastic>
                <truck skin="afternoon">-554236545.8829889</truck>
                <arrow>riding</arrow>
                <world>1019387530</world>
                <universe led="small">
                  <!--everything train-->forget
                </universe>
                <wise>opinion</wise>
                <progress>religious</progress>
              </plastic>
              <wherever>-482150725</wherever>
              <driven>due</driven>
              <rope lake="needle">heart</rope>
              <coat however="another">-696575458.4007263</coat>
            </world>
            <alike>-1548369962.2233067</alike>
            <making porch="gave">ants</making>
          </raw>
          <properly>1376700242</properly>
          <young>617140671</young>
          <name>kind
                      <!--wing yellow soil scientific amount taken-->
          </name>
          <crowd>known</crowd>
        </shape>
        <trip bottle="building">
          <!--same-->danger
        </trip>
        <!--success brown instead-->
        <loss egg="smallest">leaving</loss>
        <!--worried nobody-->
      </ants>
      <so mile="main">serve</so>
      <farther>partly</farther>
      <rather standard="daughter">
        <!--bone-->-572173481.9584856
      </rather>
      <purpose more="warm">
        <!--writer-->-212159828
      </purpose>
      <rubber>876373209</rubber>
    </various>
    <neck earn="college">dot</neck>
    <else speak="plural">hurt</else>
    <they>full</they>
    <!--highest-->
    <black>-482207114.1145582</black>
    <none>-1747293785.048098</none>
  </something>
</start>